spotify_playlist_recommender/__init__.py
spotify_playlist_recommender/api.py
spotify_playlist_recommender/auth.py
spotify_playlist_recommender-2.0.0.dist-info/METADATA
spotify_playlist_recommender-2.0.0.dist-info/WHEEL
spotify_playlist_recommender-2.0.0.dist-info/top_level.txt
spotify_playlist_recommender-2.0.0.dist-info/RECORD
