Metadata-Version: 2.1
Name: spotify-playlist-recommender
Version: 2.0.0
Summary: Python package which takes the songs of a greater playlist as starting point to make recommendations of songs based on up to 5 specific songs within that playlist, using K-Nearest-Neighbors Technique
Home-page: https://github.com/nikolas-virionis/spotify-api
Author: Nikolas Virionis
Author-email: nikolas.virionis@bandtec.com.br
License: UNKNOWN
Platform: UNKNOWN
Classifier: Programming Language :: Python :: 3
Classifier: Programming Language :: Python :: 3.8
Classifier: Topic :: Software Development :: Libraries :: Python Modules
Classifier: Operating System :: OS Independent
Requires-Python: >=3
Requires-Dist: pandas
Requires-Dist: requests
Requires-Dist: webbrowser
Provides-Extra: dev
Requires-Dist: check-manifest ; extra == 'dev'
Requires-Dist: pytest (>=3.7) ; extra == 'dev'
Requires-Dist: twine ; extra == 'dev'
